laco/__init__.py
laco/_env.py
laco/_io.py
laco/_lazy.py
laco/_overrides.py
laco/_resolvers.py
laco/cli.py
laco/handler.py
laco/keys.py
laco/language.py
laco/ops.py
laco/py.typed
laco/utils.py
laco/examples/mlp.py
laco-0.0.6.dist-info/licenses/LICENSE
laco-0.0.6.dist-info/METADATA
laco-0.0.6.dist-info/WHEEL
laco-0.0.6.dist-info/entry_points.txt
laco-0.0.6.dist-info/top_level.txt
laco-0.0.6.dist-info/RECORD
