Metadata-Version: 2.4
Name: laco
Version: 0.0.6
Summary: Lazy configurations for reproducible deep learning experiments.
Author-email: Kurt Stolle <kurt@khws.io>
Keywords: perception,computer vision,deep learning,object detection,instance segmentation,semantic segmentation
Classifier: Development Status :: 4 - Beta
Classifier: Programming Language :: Python
Classifier: Programming Language :: Python :: 3.12
Classifier: Programming Language :: Python :: Implementation :: CPython
Classifier: Operating System :: OS Independent
Classifier: Intended Audience :: Developers
Classifier: Topic :: Software Development :: Libraries :: Python Modules
Requires-Python: >=3.12
License-File: LICENSE
Requires-Dist: omegaconf
Requires-Dist: setuptools
Requires-Dist: regex
Requires-Dist: hydra-core
Requires-Dist: expath>=0.0.5
Requires-Dist: wandb>=0.19.6
Dynamic: license-file
